{
  "leads": [
    {
      "symbol": "DF/USDT",
      "anomalyId": "DF_1753996761949",
      "tradeType": "Long",
      "volumeLeverage": 13.6,
      "outcome": "consolidation",
      "converted": false,
      "watchlistTime": "2025-07-31T21:19:21.949Z",
      "lifetimeMinutes": 0,
      "createdAt": "2025-07-31T21:19:34.344Z"
    },
    {
      "symbol": "DF/USDT",
      "anomalyId": "DF_1753997023021",
      "tradeType": "Long",
      "volumeLeverage": 13.6,
      "outcome": "consolidation",
      "converted": false,
      "watchlistTime": "2025-07-31T21:23:43.021Z",
      "lifetimeMinutes": 0,
      "createdAt": "2025-07-31T21:24:04.372Z"
    },
    {
      "symbol": "DF/USDT",
      "anomalyId": "DF_1753997322976",
      "tradeType": "Long",
      "volumeLeverage": 13.6,
      "outcome": "consolidation",
      "converted": false,
      "watchlistTime": "2025-07-31T21:28:42.976Z",
      "lifetimeMinutes": 0,
      "createdAt": "2025-07-31T21:29:04.446Z"
    },
    {
      "symbol": "WOO/USDT",
      "anomalyId": "WOO_1753997524299",
      "tradeType": "Long",
      "volumeLeverage": 18.3,
      "outcome": "consolidation",
      "converted": false,
      "watchlistTime": "2025-07-31T21:32:04.299Z",
      "lifetimeMinutes": 1,
      "createdAt": "2025-07-31T21:32:34.494Z"
    },
    {
      "symbol": "TOKEN/USDT",
      "anomalyId": "TOKEN_1753997586276",
      "tradeType": "Long",
      "volumeLeverage": 15.9,
      "outcome": "consolidation",
      "converted": false,
      "watchlistTime": "2025-07-31T21:33:06.276Z",
      "lifetimeMinutes": 0,
      "createdAt": "2025-07-31T21:33:35.957Z"
    },
    {
      "symbol": "WOO/USDT",
      "anomalyId": "WOO_1753997824994",
      "tradeType": "Long",
      "volumeLeverage": 18.3,
      "outcome": "consolidation",
      "converted": false,
      "watchlistTime": "2025-07-31T21:37:04.994Z",
      "lifetimeMinutes": 0,
      "createdAt": "2025-07-31T21:37:34.835Z"
    },
    {
      "symbol": "TOKEN/USDT",
      "anomalyId": "TOKEN_1753997889696",
      "tradeType": "Long",
      "volumeLeverage": 15.9,
      "outcome": "consolidation",
      "converted": false,
      "watchlistTime": "2025-07-31T21:38:09.696Z",
      "lifetimeMinutes": 0,
      "createdAt": "2025-07-31T21:38:34.618Z"
    },
    {
      "symbol": "WOO/USDT",
      "anomalyId": "WOO_1753998133984",
      "tradeType": "Long",
      "volumeLeverage": 18.3,
      "outcome": "consolidation",
      "converted": false,
      "watchlistTime": "2025-07-31T21:42:13.984Z",
      "lifetimeMinutes": 0,
      "createdAt": "2025-07-31T21:42:42.774Z"
    },
    {
      "symbol": "TOKEN/USDT",
      "anomalyId": "TOKEN_1753998239889",
      "tradeType": "Long",
      "volumeLeverage": 15.9,
      "outcome": "consolidation",
      "converted": false,
      "watchlistTime": "2025-07-31T21:43:59.889Z",
      "lifetimeMinutes": 0,
      "createdAt": "2025-07-31T21:44:04.746Z"
    },
    {
      "symbol": "BCH/USDT",
      "anomalyId": "BCH_1753998366936",
      "tradeType": "Short",
      "volumeLeverage": 16.8,
      "outcome": "consolidation",
      "converted": false,
      "watchlistTime": "2025-07-31T21:46:06.936Z",
      "lifetimeMinutes": 0,
      "createdAt": "2025-07-31T21:46:34.958Z"
    },
    {
      "symbol": "BCH/USDT",
      "anomalyId": "BCH_1753998667252",
      "tradeType": "Short",
      "volumeLeverage": 16.8,
      "outcome": "consolidation",
      "converted": false,
      "watchlistTime": "2025-07-31T21:51:07.252Z",
      "lifetimeMinutes": 0,
      "createdAt": "2025-07-31T21:51:34.781Z"
    },
    {
      "symbol": "BCH/USDT",
      "anomalyId": "BCH_1753998966896",
      "tradeType": "Short",
      "volumeLeverage": 16.8,
      "outcome": "consolidation",
      "converted": false,
      "watchlistTime": "2025-07-31T21:56:06.896Z",
      "lifetimeMinutes": 0,
      "createdAt": "2025-07-31T21:56:34.906Z"
    },
    {
      "symbol": "GMX/USDT",
      "anomalyId": "GMX_1753996648116",
      "tradeType": "Long",
      "volumeLeverage": 9.7,
      "outcome": "cancel",
      "converted": false,
      "watchlistTime": "2025-07-31T21:17:28.117Z",
      "lifetimeMinutes": 43,
      "createdAt": "2025-07-31T22:00:04.905Z"
    },
    {
      "symbol": "JTO/USDT",
      "anomalyId": "JTO_1753999314493",
      "tradeType": "Long",
      "volumeLeverage": 14.2,
      "outcome": "consolidation",
      "converted": false,
      "watchlistTime": "2025-07-31T22:01:54.493Z",
      "lifetimeMinutes": 0,
      "createdAt": "2025-07-31T22:02:04.982Z"
    },
    {
      "symbol": "ZEC/USDT",
      "anomalyId": "ZEC_1753999314677",
      "tradeType": "Long",
      "volumeLeverage": 12.8,
      "outcome": "consolidation",
      "converted": false,
      "watchlistTime": "2025-07-31T22:01:54.677Z",
      "lifetimeMinutes": 0,
      "createdAt": "2025-07-31T22:02:04.984Z"
    },
    {
      "symbol": "SOON/USDT",
      "anomalyId": "SOON_1753999455661",
      "tradeType": "Long",
      "volumeLeverage": 11.5,
      "outcome": "consolidation",
      "converted": false,
      "watchlistTime": "2025-07-31T22:04:15.661Z",
      "lifetimeMinutes": 0,
      "createdAt": "2025-07-31T22:04:35.050Z"
    },
    {
      "symbol": "GUN/USDT",
      "anomalyId": "GUN_1753999458897",
      "tradeType": "Long",
      "volumeLeverage": 8.2,
      "outcome": "consolidation",
      "converted": false,
      "watchlistTime": "2025-07-31T22:04:18.897Z",
      "lifetimeMinutes": 0,
      "createdAt": "2025-07-31T22:04:35.213Z"
    },
    {
      "symbol": "JTO/USDT",
      "anomalyId": "JTO_1753999585573",
      "tradeType": "Long",
      "volumeLeverage": 14.2,
      "outcome": "consolidation",
      "converted": false,
      "watchlistTime": "2025-07-31T22:06:25.573Z",
      "lifetimeMinutes": 0,
      "createdAt": "2025-07-31T22:06:35.211Z"
    },
    {
      "symbol": "ZEC/USDT",
      "anomalyId": "ZEC_1753999585576",
      "tradeType": "Long",
      "volumeLeverage": 12.8,
      "outcome": "consolidation",
      "converted": false,
      "watchlistTime": "2025-07-31T22:06:25.576Z",
      "lifetimeMinutes": 0,
      "createdAt": "2025-07-31T22:06:35.214Z"
    },
    {
      "symbol": "GUN/USDT",
      "anomalyId": "GUN_1753999738697",
      "tradeType": "Long",
      "volumeLeverage": 8.2,
      "outcome": "consolidation",
      "converted": false,
      "watchlistTime": "2025-07-31T22:08:58.697Z",
      "lifetimeMinutes": 0,
      "createdAt": "2025-07-31T22:09:05.237Z"
    },
    {
      "symbol": "SOON/USDT",
      "anomalyId": "SOON_1753999732120",
      "tradeType": "Long",
      "volumeLeverage": 11.5,
      "outcome": "consolidation",
      "converted": false,
      "watchlistTime": "2025-07-31T22:08:52.120Z",
      "lifetimeMinutes": 0,
      "createdAt": "2025-07-31T22:09:05.241Z"
    },
    {
      "symbol": "ZEC/USDT",
      "anomalyId": "ZEC_1753999884696",
      "tradeType": "Long",
      "volumeLeverage": 12.8,
      "outcome": "consolidation",
      "converted": false,
      "watchlistTime": "2025-07-31T22:11:24.696Z",
      "lifetimeMinutes": 0,
      "createdAt": "2025-07-31T22:11:35.104Z"
    },
    {
      "symbol": "JTO/USDT",
      "anomalyId": "JTO_1753999884699",
      "tradeType": "Long",
      "volumeLeverage": 14.2,
      "outcome": "consolidation",
      "converted": false,
      "watchlistTime": "2025-07-31T22:11:24.699Z",
      "lifetimeMinutes": 0,
      "createdAt": "2025-07-31T22:11:35.106Z"
    },
    {
      "symbol": "SOON/USDT",
      "anomalyId": "SOON_1754000018251",
      "tradeType": "Long",
      "volumeLeverage": 11.5,
      "outcome": "consolidation",
      "converted": false,
      "watchlistTime": "2025-07-31T22:13:38.251Z",
      "lifetimeMinutes": 0,
      "createdAt": "2025-07-31T22:14:05.206Z"
    },
    {
      "symbol": "GUN/USDT",
      "anomalyId": "GUN_1754000023079",
      "tradeType": "Long",
      "volumeLeverage": 8.2,
      "outcome": "consolidation",
      "converted": false,
      "watchlistTime": "2025-07-31T22:13:43.079Z",
      "lifetimeMinutes": 0,
      "createdAt": "2025-07-31T22:14:05.208Z"
    },
    {
      "symbol": "WLD/USDT",
      "anomalyId": "WLD_1754000174377",
      "tradeType": "Long",
      "volumeLeverage": 10.5,
      "outcome": "consolidation",
      "converted": false,
      "watchlistTime": "2025-07-31T22:16:14.377Z",
      "lifetimeMinutes": 0,
      "createdAt": "2025-07-31T22:16:35.371Z"
    },
    {
      "symbol": "SCRT/USDT",
      "anomalyId": "SCRT_1754000277214",
      "tradeType": "Long",
      "volumeLeverage": 11.8,
      "outcome": "consolidation",
      "converted": false,
      "watchlistTime": "2025-07-31T22:17:57.214Z",
      "lifetimeMinutes": 0,
      "createdAt": "2025-07-31T22:18:05.676Z"
    },
    {
      "symbol": "WLD/USDT",
      "anomalyId": "WLD_1754000474322",
      "tradeType": "Long",
      "volumeLeverage": 10.5,
      "outcome": "consolidation",
      "converted": false,
      "watchlistTime": "2025-07-31T22:21:14.322Z",
      "lifetimeMinutes": 0,
      "createdAt": "2025-07-31T22:21:36.527Z"
    },
    {
      "symbol": "SCRT/USDT",
      "anomalyId": "SCRT_1754000582689",
      "tradeType": "Long",
      "volumeLeverage": 11.8,
      "outcome": "consolidation",
      "converted": false,
      "watchlistTime": "2025-07-31T22:23:02.689Z",
      "lifetimeMinutes": 0,
      "createdAt": "2025-07-31T22:23:05.198Z"
    },
    {
      "symbol": "WLD/USDT",
      "anomalyId": "WLD_1754000773650",
      "tradeType": "Long",
      "volumeLeverage": 10.5,
      "outcome": "consolidation",
      "converted": false,
      "watchlistTime": "2025-07-31T22:26:13.650Z",
      "lifetimeMinutes": 0,
      "createdAt": "2025-07-31T22:26:35.320Z"
    },
    {
      "symbol": "SCRT/USDT",
      "anomalyId": "SCRT_1754000872487",
      "tradeType": "Long",
      "volumeLeverage": 11.8,
      "outcome": "consolidation",
      "converted": false,
      "watchlistTime": "2025-07-31T22:27:52.487Z",
      "lifetimeMinutes": 0,
      "createdAt": "2025-07-31T22:28:05.482Z"
    },
    {
      "symbol": "ROSE/USDT",
      "anomalyId": "ROSE_1754001109749",
      "tradeType": "Long",
      "volumeLeverage": 8.8,
      "outcome": "consolidation",
      "converted": false,
      "watchlistTime": "2025-07-31T22:31:49.749Z",
      "lifetimeMinutes": 0,
      "createdAt": "2025-07-31T22:32:05.652Z"
    },
    {
      "symbol": "MDT/USDT",
      "anomalyId": "MDT_1754001235701",
      "tradeType": "Short",
      "volumeLeverage": 10.2,
      "outcome": "consolidation",
      "converted": false,
      "watchlistTime": "2025-07-31T22:33:55.701Z",
      "lifetimeMinutes": 0,
      "createdAt": "2025-07-31T22:34:05.537Z"
    },
    {
      "symbol": "ROSE/USDT",
      "anomalyId": "ROSE_1754001407440",
      "tradeType": "Long",
      "volumeLeverage": 8.8,
      "outcome": "consolidation",
      "converted": false,
      "watchlistTime": "2025-07-31T22:36:47.440Z",
      "lifetimeMinutes": 0,
      "createdAt": "2025-07-31T22:37:05.417Z"
    },
    {
      "symbol": "MDT/USDT",
      "anomalyId": "MDT_1754001532492",
      "tradeType": "Short",
      "volumeLeverage": 10.2,
      "outcome": "consolidation",
      "converted": false,
      "watchlistTime": "2025-07-31T22:38:52.492Z",
      "lifetimeMinutes": 0,
      "createdAt": "2025-07-31T22:39:05.575Z"
    },
    {
      "symbol": "ROSE/USDT",
      "anomalyId": "ROSE_1754001711289",
      "tradeType": "Long",
      "volumeLeverage": 8.8,
      "outcome": "consolidation",
      "converted": false,
      "watchlistTime": "2025-07-31T22:41:51.289Z",
      "lifetimeMinutes": 0,
      "createdAt": "2025-07-31T22:42:05.549Z"
    },
    {
      "symbol": "MDT/USDT",
      "anomalyId": "MDT_1754001841969",
      "tradeType": "Short",
      "volumeLeverage": 10.2,
      "outcome": "consolidation",
      "converted": false,
      "watchlistTime": "2025-07-31T22:44:01.969Z",
      "lifetimeMinutes": 0,
      "createdAt": "2025-07-31T22:44:05.554Z"
    },
    {
      "symbol": "ATH/USDT",
      "anomalyId": "ATH_1754001993716",
      "tradeType": "Long",
      "volumeLeverage": 20.3,
      "outcome": "consolidation",
      "converted": false,
      "watchlistTime": "2025-07-31T22:46:33.716Z",
      "lifetimeMinutes": 0,
      "createdAt": "2025-07-31T22:46:35.621Z"
    },
    {
      "symbol": "AMP/USDT",
      "anomalyId": "AMP_1754001996718",
      "tradeType": "Long",
      "volumeLeverage": 12.6,
      "outcome": "consolidation",
      "converted": false,
      "watchlistTime": "2025-07-31T22:46:36.718Z",
      "lifetimeMinutes": 0,
      "createdAt": "2025-07-31T22:47:06.061Z"
    },
    {
      "symbol": "ATH/USDT",
      "anomalyId": "ATH_1754002296660",
      "tradeType": "Long",
      "volumeLeverage": 20.3,
      "outcome": "consolidation",
      "converted": false,
      "watchlistTime": "2025-07-31T22:51:36.660Z",
      "lifetimeMinutes": 0,
      "createdAt": "2025-07-31T22:52:05.802Z"
    },
    {
      "symbol": "AMP/USDT",
      "anomalyId": "AMP_1754002300780",
      "tradeType": "Long",
      "volumeLeverage": 12.6,
      "outcome": "consolidation",
      "converted": false,
      "watchlistTime": "2025-07-31T22:51:40.780Z",
      "lifetimeMinutes": 0,
      "createdAt": "2025-07-31T22:52:05.803Z"
    },
    {
      "symbol": "ATH/USDT",
      "anomalyId": "ATH_1754002593824",
      "tradeType": "Long",
      "volumeLeverage": 20.3,
      "outcome": "consolidation",
      "converted": false,
      "watchlistTime": "2025-07-31T22:56:33.824Z",
      "lifetimeMinutes": 0,
      "createdAt": "2025-07-31T22:56:36.261Z"
    },
    {
      "symbol": "AMP/USDT",
      "anomalyId": "AMP_1754002597666",
      "tradeType": "Long",
      "volumeLeverage": 12.6,
      "outcome": "consolidation",
      "converted": false,
      "watchlistTime": "2025-07-31T22:56:37.666Z",
      "lifetimeMinutes": 0,
      "createdAt": "2025-07-31T22:57:05.797Z"
    },
    {
      "symbol": "1INCH/USDT",
      "anomalyId": "1INCH_1754001992325",
      "tradeType": "Long",
      "volumeLeverage": 12.7,
      "outcome": "entry",
      "converted": true,
      "watchlistTime": "2025-07-31T22:46:32.325Z",
      "lifetimeMinutes": 29,
      "createdAt": "2025-07-31T23:15:06.038Z"
    },
    {
      "symbol": "ZEREBRO/USDT",
      "anomalyId": "ZEREBRO_1754003909809",
      "tradeType": "Short",
      "volumeLeverage": 8,
      "outcome": "consolidation",
      "converted": false,
      "watchlistTime": "2025-07-31T23:18:29.809Z",
      "lifetimeMinutes": 0,
      "createdAt": "2025-07-31T23:18:36.654Z"
    },
    {
      "symbol": "ZEREBRO/USDT",
      "anomalyId": "ZEREBRO_1754004206650",
      "tradeType": "Short",
      "volumeLeverage": 8,
      "outcome": "consolidation",
      "converted": false,
      "watchlistTime": "2025-07-31T23:23:26.650Z",
      "lifetimeMinutes": 0,
      "createdAt": "2025-07-31T23:23:36.724Z"
    },
    {
      "symbol": "ZEREBRO/USDT",
      "anomalyId": "ZEREBRO_1754004508808",
      "tradeType": "Short",
      "volumeLeverage": 8,
      "outcome": "consolidation",
      "converted": false,
      "watchlistTime": "2025-07-31T23:28:28.808Z",
      "lifetimeMinutes": 0,
      "createdAt": "2025-07-31T23:28:36.688Z"
    },
    {
      "symbol": "SLERF/USDT",
      "anomalyId": "SLERF_1753999432514",
      "tradeType": "Long",
      "volumeLeverage": 9.5,
      "outcome": "cancel",
      "converted": false,
      "watchlistTime": "2025-07-31T22:03:52.514Z",
      "lifetimeMinutes": 86,
      "createdAt": "2025-07-31T23:30:06.941Z"
    },
    {
      "symbol": "FLUX/USDT",
      "anomalyId": "FLUX_1754003837769",
      "tradeType": "Long",
      "volumeLeverage": 28.8,
      "outcome": "cancel",
      "converted": false,
      "watchlistTime": "2025-07-31T23:17:17.769Z",
      "lifetimeMinutes": 13,
      "createdAt": "2025-07-31T23:30:07.105Z"
    },
    {
      "symbol": "CKB/USDT",
      "anomalyId": "CKB_1754005599092",
      "tradeType": "Long",
      "volumeLeverage": 8.5,
      "outcome": "consolidation",
      "converted": false,
      "watchlistTime": "2025-07-31T23:46:39.092Z",
      "lifetimeMinutes": 0,
      "createdAt": "2025-07-31T23:47:06.437Z"
    },
    {
      "symbol": "USUAL/USDT",
      "anomalyId": "USUAL_1754005639714",
      "tradeType": "Long",
      "volumeLeverage": 9.7,
      "outcome": "consolidation",
      "converted": false,
      "watchlistTime": "2025-07-31T23:47:19.714Z",
      "lifetimeMinutes": 0,
      "createdAt": "2025-07-31T23:47:36.460Z"
    },
    {
      "symbol": "LUMIA/USDT",
      "anomalyId": "LUMIA_1754005711631",
      "tradeType": "Long",
      "volumeLeverage": 9.4,
      "outcome": "consolidation",
      "converted": false,
      "watchlistTime": "2025-07-31T23:48:31.631Z",
      "lifetimeMinutes": 0,
      "createdAt": "2025-07-31T23:48:36.519Z"
    },
    {
      "symbol": "CKB/USDT",
      "anomalyId": "CKB_1754005897358",
      "tradeType": "Long",
      "volumeLeverage": 8.5,
      "outcome": "consolidation",
      "converted": false,
      "watchlistTime": "2025-07-31T23:51:37.358Z",
      "lifetimeMinutes": 0,
      "createdAt": "2025-07-31T23:52:06.568Z"
    },
    {
      "symbol": "USUAL/USDT",
      "anomalyId": "USUAL_1754005937545",
      "tradeType": "Long",
      "volumeLeverage": 9.7,
      "outcome": "consolidation",
      "converted": false,
      "watchlistTime": "2025-07-31T23:52:17.545Z",
      "lifetimeMinutes": 0,
      "createdAt": "2025-07-31T23:52:36.577Z"
    },
    {
      "symbol": "LUMIA/USDT",
      "anomalyId": "LUMIA_1754006008056",
      "tradeType": "Long",
      "volumeLeverage": 9.4,
      "outcome": "consolidation",
      "converted": false,
      "watchlistTime": "2025-07-31T23:53:28.056Z",
      "lifetimeMinutes": 0,
      "createdAt": "2025-07-31T23:53:36.626Z"
    },
    {
      "symbol": "CKB/USDT",
      "anomalyId": "CKB_1754006202193",
      "tradeType": "Long",
      "volumeLeverage": 8.5,
      "outcome": "consolidation",
      "converted": false,
      "watchlistTime": "2025-07-31T23:56:42.193Z",
      "lifetimeMinutes": 0,
      "createdAt": "2025-07-31T23:57:06.604Z"
    },
    {
      "symbol": "USUAL/USDT",
      "anomalyId": "USUAL_1754006242500",
      "tradeType": "Long",
      "volumeLeverage": 9.7,
      "outcome": "consolidation",
      "converted": false,
      "watchlistTime": "2025-07-31T23:57:22.500Z",
      "lifetimeMinutes": 0,
      "createdAt": "2025-07-31T23:57:36.626Z"
    },
    {
      "symbol": "LUMIA/USDT",
      "anomalyId": "LUMIA_1754006313407",
      "tradeType": "Long",
      "volumeLeverage": 9.4,
      "outcome": "consolidation",
      "converted": false,
      "watchlistTime": "2025-07-31T23:58:33.407Z",
      "lifetimeMinutes": 0,
      "createdAt": "2025-07-31T23:58:36.654Z"
    },
    {
      "symbol": "S/USDT",
      "anomalyId": "S_1754006477284",
      "tradeType": "Long",
      "volumeLeverage": 10,
      "outcome": "consolidation",
      "converted": false,
      "watchlistTime": "2025-08-01T00:01:17.284Z",
      "lifetimeMinutes": 0,
      "createdAt": "2025-08-01T00:01:36.837Z"
    },
    {
      "symbol": "S/USDT",
      "anomalyId": "S_1754006777581",
      "tradeType": "Long",
      "volumeLeverage": 10,
      "outcome": "consolidation",
      "converted": false,
      "watchlistTime": "2025-08-01T00:06:17.581Z",
      "lifetimeMinutes": 0,
      "createdAt": "2025-08-01T00:06:36.747Z"
    },
    {
      "symbol": "S/USDT",
      "anomalyId": "S_1754007077501",
      "tradeType": "Long",
      "volumeLeverage": 10,
      "outcome": "consolidation",
      "converted": false,
      "watchlistTime": "2025-08-01T00:11:17.501Z",
      "lifetimeMinutes": 0,
      "createdAt": "2025-08-01T00:11:36.845Z"
    },
    {
      "symbol": "ZIL/USDT",
      "anomalyId": "ZIL_1754005603973",
      "tradeType": "Long",
      "volumeLeverage": 11.6,
      "outcome": "cancel",
      "converted": false,
      "watchlistTime": "2025-07-31T23:46:43.973Z",
      "lifetimeMinutes": 25,
      "createdAt": "2025-08-01T00:12:06.935Z"
    },
    {
      "symbol": "OXT/USDT",
      "anomalyId": "OXT_1754005691067",
      "tradeType": "Long",
      "volumeLeverage": 8.2,
      "outcome": "cancel",
      "converted": false,
      "watchlistTime": "2025-07-31T23:48:11.067Z",
      "lifetimeMinutes": 27,
      "createdAt": "2025-08-01T00:15:06.851Z"
    },
    {
      "symbol": "BNSOL/USDT",
      "anomalyId": "BNSOL_1754005573970",
      "tradeType": "Long",
      "volumeLeverage": 8,
      "outcome": "cancel",
      "converted": false,
      "watchlistTime": "2025-07-31T23:46:13.970Z",
      "lifetimeMinutes": 29,
      "createdAt": "2025-08-01T00:15:07.030Z"
    },
    {
      "symbol": "KAS/USDT",
      "anomalyId": "KAS_1754007371263",
      "tradeType": "Long",
      "volumeLeverage": 11.2,
      "outcome": "consolidation",
      "converted": false,
      "watchlistTime": "2025-08-01T00:16:11.263Z",
      "lifetimeMinutes": 0,
      "createdAt": "2025-08-01T00:16:36.837Z"
    },
    {
      "symbol": "KAIA/USDT",
      "anomalyId": "KAIA_1754007379191",
      "tradeType": "Long",
      "volumeLeverage": 11.9,
      "outcome": "consolidation",
      "converted": false,
      "watchlistTime": "2025-08-01T00:16:19.191Z",
      "lifetimeMinutes": 0,
      "createdAt": "2025-08-01T00:16:37.022Z"
    },
    {
      "symbol": "A/USDT",
      "anomalyId": "A_1754007380639",
      "tradeType": "Long",
      "volumeLeverage": 9.4,
      "outcome": "consolidation",
      "converted": false,
      "watchlistTime": "2025-08-01T00:16:20.639Z",
      "lifetimeMinutes": 0,
      "createdAt": "2025-08-01T00:16:37.023Z"
    },
    {
      "symbol": "XEC/USDT",
      "anomalyId": "XEC_1754007390228",
      "tradeType": "Long",
      "volumeLeverage": 9.7,
      "outcome": "consolidation",
      "converted": false,
      "watchlistTime": "2025-08-01T00:16:30.228Z",
      "lifetimeMinutes": 0,
      "createdAt": "2025-08-01T00:16:37.024Z"
    },
    {
      "symbol": "SC/USDT",
      "anomalyId": "SC_1754007409649",
      "tradeType": "Short",
      "volumeLeverage": 30.8,
      "outcome": "consolidation",
      "converted": false,
      "watchlistTime": "2025-08-01T00:16:49.649Z",
      "lifetimeMinutes": 0,
      "createdAt": "2025-08-01T00:17:06.906Z"
    },
    {
      "symbol": "DGB/USDT",
      "anomalyId": "DGB_1754007412964",
      "tradeType": "Long",
      "volumeLeverage": 25.4,
      "outcome": "consolidation",
      "converted": false,
      "watchlistTime": "2025-08-01T00:16:52.964Z",
      "lifetimeMinutes": 0,
      "createdAt": "2025-08-01T00:17:07.089Z"
    },
    {
      "symbol": "ONE/USDT",
      "anomalyId": "ONE_1754007414338",
      "tradeType": "Long",
      "volumeLeverage": 8.2,
      "outcome": "consolidation",
      "converted": false,
      "watchlistTime": "2025-08-01T00:16:54.338Z",
      "lifetimeMinutes": 0,
      "createdAt": "2025-08-01T00:17:07.090Z"
    },
    {
      "symbol": "STRAX/USDT",
      "anomalyId": "STRAX_1754007433040",
      "tradeType": "Long",
      "volumeLeverage": 26.7,
      "outcome": "consolidation",
      "converted": false,
      "watchlistTime": "2025-08-01T00:17:13.040Z",
      "lifetimeMinutes": 0,
      "createdAt": "2025-08-01T00:17:36.833Z"
    },
    {
      "symbol": "IQ/USDT",
      "anomalyId": "IQ_1754007443531",
      "tradeType": "Short",
      "volumeLeverage": 40.5,
      "outcome": "consolidation",
      "converted": false,
      "watchlistTime": "2025-08-01T00:17:23.531Z",
      "lifetimeMinutes": 0,
      "createdAt": "2025-08-01T00:17:37.016Z"
    },
    {
      "symbol": "DENT/USDT",
      "anomalyId": "DENT_1754007447946",
      "tradeType": "Long",
      "volumeLeverage": 10.7,
      "outcome": "consolidation",
      "converted": false,
      "watchlistTime": "2025-08-01T00:17:27.947Z",
      "lifetimeMinutes": 0,
      "createdAt": "2025-08-01T00:17:37.017Z"
    },
    {
      "symbol": "JOE/USDT",
      "anomalyId": "JOE_1754007453653",
      "tradeType": "Long",
      "volumeLeverage": 8.2,
      "outcome": "consolidation",
      "converted": false,
      "watchlistTime": "2025-08-01T00:17:33.653Z",
      "lifetimeMinutes": 0,
      "createdAt": "2025-08-01T00:17:37.018Z"
    },
    {
      "symbol": "MBL/USDT",
      "anomalyId": "MBL_1754007472545",
      "tradeType": "Short",
      "volumeLeverage": 8.6,
      "outcome": "consolidation",
      "converted": false,
      "watchlistTime": "2025-08-01T00:17:52.545Z",
      "lifetimeMinutes": 0,
      "createdAt": "2025-08-01T00:18:06.853Z"
    },
    {
      "symbol": "JOE/USDT",
      "anomalyId": "JOE_1754007472582",
      "tradeType": "Long",
      "volumeLeverage": 8.2,
      "outcome": "consolidation",
      "converted": false,
      "watchlistTime": "2025-08-01T00:17:52.582Z",
      "lifetimeMinutes": 0,
      "createdAt": "2025-08-01T00:18:07.037Z"
    },
    {
      "symbol": "HOOK/USDT",
      "anomalyId": "HOOK_1754007499971",
      "tradeType": "Long",
      "volumeLeverage": 9.1,
      "outcome": "consolidation",
      "converted": false,
      "watchlistTime": "2025-08-01T00:18:19.971Z",
      "lifetimeMinutes": 0,
      "createdAt": "2025-08-01T00:18:36.864Z"
    },
    {
      "symbol": "ATA/USDT",
      "anomalyId": "ATA_1754007502764",
      "tradeType": "Long",
      "volumeLeverage": 9.4,
      "outcome": "consolidation",
      "converted": false,
      "watchlistTime": "2025-08-01T00:18:22.764Z",
      "lifetimeMinutes": 0,
      "createdAt": "2025-08-01T00:18:37.052Z"
    },
    {
      "symbol": "KAS/USDT",
      "anomalyId": "KAS_1754007670968",
      "tradeType": "Long",
      "volumeLeverage": 11.2,
      "outcome": "consolidation",
      "converted": false,
      "watchlistTime": "2025-08-01T00:21:10.968Z",
      "lifetimeMinutes": 0,
      "createdAt": "2025-08-01T00:21:37.024Z"
    },
    {
      "symbol": "KAIA/USDT",
      "anomalyId": "KAIA_1754007680722",
      "tradeType": "Long",
      "volumeLeverage": 11.9,
      "outcome": "consolidation",
      "converted": false,
      "watchlistTime": "2025-08-01T00:21:20.722Z",
      "lifetimeMinutes": 0,
      "createdAt": "2025-08-01T00:21:37.209Z"
    },
    {
      "symbol": "A/USDT",
      "anomalyId": "A_1754007680869",
      "tradeType": "Long",
      "volumeLeverage": 9.4,
      "outcome": "consolidation",
      "converted": false,
      "watchlistTime": "2025-08-01T00:21:20.869Z",
      "lifetimeMinutes": 0,
      "createdAt": "2025-08-01T00:21:37.211Z"
    },
    {
      "symbol": "XEC/USDT",
      "anomalyId": "XEC_1754007691214",
      "tradeType": "Long",
      "volumeLeverage": 9.7,
      "outcome": "consolidation",
      "converted": false,
      "watchlistTime": "2025-08-01T00:21:31.214Z",
      "lifetimeMinutes": 0,
      "createdAt": "2025-08-01T00:21:37.212Z"
    },
    {
      "symbol": "SC/USDT",
      "anomalyId": "SC_1754007711125",
      "tradeType": "Short",
      "volumeLeverage": 30.8,
      "outcome": "consolidation",
      "converted": false,
      "watchlistTime": "2025-08-01T00:21:51.125Z",
      "lifetimeMinutes": 0,
      "createdAt": "2025-08-01T00:22:06.945Z"
    },
    {
      "symbol": "DGB/USDT",
      "anomalyId": "DGB_1754007714028",
      "tradeType": "Long",
      "volumeLeverage": 25.4,
      "outcome": "consolidation",
      "converted": false,
      "watchlistTime": "2025-08-01T00:21:54.028Z",
      "lifetimeMinutes": 0,
      "createdAt": "2025-08-01T00:22:07.130Z"
    },
    {
      "symbol": "ONE/USDT",
      "anomalyId": "ONE_1754007715388",
      "tradeType": "Long",
      "volumeLeverage": 8.2,
      "outcome": "consolidation",
      "converted": false,
      "watchlistTime": "2025-08-01T00:21:55.388Z",
      "lifetimeMinutes": 0,
      "createdAt": "2025-08-01T00:22:07.131Z"
    },
    {
      "symbol": "STRAX/USDT",
      "anomalyId": "STRAX_1754007734650",
      "tradeType": "Long",
      "volumeLeverage": 26.7,
      "outcome": "consolidation",
      "converted": false,
      "watchlistTime": "2025-08-01T00:22:14.650Z",
      "lifetimeMinutes": 0,
      "createdAt": "2025-08-01T00:22:37.002Z"
    },
    {
      "symbol": "IQ/USDT",
      "anomalyId": "IQ_1754007744746",
      "tradeType": "Short",
      "volumeLeverage": 40.5,
      "outcome": "consolidation",
      "converted": false,
      "watchlistTime": "2025-08-01T00:22:24.746Z",
      "lifetimeMinutes": 0,
      "createdAt": "2025-08-01T00:22:37.003Z"
    },
    {
      "symbol": "DENT/USDT",
      "anomalyId": "DENT_1754007750564",
      "tradeType": "Long",
      "volumeLeverage": 10.7,
      "outcome": "consolidation",
      "converted": false,
      "watchlistTime": "2025-08-01T00:22:30.564Z",
      "lifetimeMinutes": 0,
      "createdAt": "2025-08-01T00:22:37.005Z"
    },
    {
      "symbol": "JOE/USDT",
      "anomalyId": "JOE_1754007754948",
      "tradeType": "Long",
      "volumeLeverage": 8.2,
      "outcome": "consolidation",
      "converted": false,
      "watchlistTime": "2025-08-01T00:22:34.948Z",
      "lifetimeMinutes": 0,
      "createdAt": "2025-08-01T00:22:37.526Z"
    },
    {
      "symbol": "MBL/USDT",
      "anomalyId": "MBL_1754007775107",
      "tradeType": "Short",
      "volumeLeverage": 8.6,
      "outcome": "consolidation",
      "converted": false,
      "watchlistTime": "2025-08-01T00:22:55.107Z",
      "lifetimeMinutes": 0,
      "createdAt": "2025-08-01T00:23:07.026Z"
    },
    {
      "symbol": "JOE/USDT",
      "anomalyId": "JOE_1754007775137",
      "tradeType": "Long",
      "volumeLeverage": 8.2,
      "outcome": "consolidation",
      "converted": false,
      "watchlistTime": "2025-08-01T00:22:55.137Z",
      "lifetimeMinutes": 0,
      "createdAt": "2025-08-01T00:23:07.027Z"
    },
    {
      "symbol": "HOOK/USDT",
      "anomalyId": "HOOK_1754007802428",
      "tradeType": "Long",
      "volumeLeverage": 9.1,
      "outcome": "consolidation",
      "converted": false,
      "watchlistTime": "2025-08-01T00:23:22.428Z",
      "lifetimeMinutes": 0,
      "createdAt": "2025-08-01T00:23:37.003Z"
    },
    {
      "symbol": "ATA/USDT",
      "anomalyId": "ATA_1754007805210",
      "tradeType": "Long",
      "volumeLeverage": 9.4,
      "outcome": "consolidation",
      "converted": false,
      "watchlistTime": "2025-08-01T00:23:25.210Z",
      "lifetimeMinutes": 0,
      "createdAt": "2025-08-01T00:23:37.005Z"
    },
    {
      "symbol": "KAS/USDT",
      "anomalyId": "KAS_1754007970650",
      "tradeType": "Long",
      "volumeLeverage": 11.2,
      "outcome": "consolidation",
      "converted": false,
      "watchlistTime": "2025-08-01T00:26:10.650Z",
      "lifetimeMinutes": 0,
      "createdAt": "2025-08-01T00:26:36.984Z"
    },
    {
      "symbol": "KAIA/USDT",
      "anomalyId": "KAIA_1754007980181",
      "tradeType": "Long",
      "volumeLeverage": 11.9,
      "outcome": "consolidation",
      "converted": false,
      "watchlistTime": "2025-08-01T00:26:20.181Z",
      "lifetimeMinutes": 0,
      "createdAt": "2025-08-01T00:26:37.171Z"
    },
    {
      "symbol": "A/USDT",
      "anomalyId": "A_1754007980313",
      "tradeType": "Long",
      "volumeLeverage": 9.4,
      "outcome": "consolidation",
      "converted": false,
      "watchlistTime": "2025-08-01T00:26:20.313Z",
      "lifetimeMinutes": 0,
      "createdAt": "2025-08-01T00:26:37.173Z"
    },
    {
      "symbol": "XEC/USDT",
      "anomalyId": "XEC_1754007990057",
      "tradeType": "Long",
      "volumeLeverage": 9.7,
      "outcome": "consolidation",
      "converted": false,
      "watchlistTime": "2025-08-01T00:26:30.057Z",
      "lifetimeMinutes": 0,
      "createdAt": "2025-08-01T00:26:37.174Z"
    },
    {
      "symbol": "SC/USDT",
      "anomalyId": "SC_1754008010309",
      "tradeType": "Short",
      "volumeLeverage": 30.8,
      "outcome": "consolidation",
      "converted": false,
      "watchlistTime": "2025-08-01T00:26:50.309Z",
      "lifetimeMinutes": 0,
      "createdAt": "2025-08-01T00:27:06.997Z"
    },
    {
      "symbol": "DGB/USDT",
      "anomalyId": "DGB_1754008013186",
      "tradeType": "Long",
      "volumeLeverage": 25.4,
      "outcome": "consolidation",
      "converted": false,
      "watchlistTime": "2025-08-01T00:26:53.186Z",
      "lifetimeMinutes": 0,
      "createdAt": "2025-08-01T00:27:07.006Z"
    },
    {
      "symbol": "ONE/USDT",
      "anomalyId": "ONE_1754008014537",
      "tradeType": "Long",
      "volumeLeverage": 8.2,
      "outcome": "consolidation",
      "converted": false,
      "watchlistTime": "2025-08-01T00:26:54.537Z",
      "lifetimeMinutes": 0,
      "createdAt": "2025-08-01T00:27:07.364Z"
    },
    {
      "symbol": "STRAX/USDT",
      "anomalyId": "STRAX_1754008034288",
      "tradeType": "Long",
      "volumeLeverage": 26.7,
      "outcome": "consolidation",
      "converted": false,
      "watchlistTime": "2025-08-01T00:27:14.288Z",
      "lifetimeMinutes": 0,
      "createdAt": "2025-08-01T00:27:37.016Z"
    },
    {
      "symbol": "IQ/USDT",
      "anomalyId": "IQ_1754008043384",
      "tradeType": "Short",
      "volumeLeverage": 40.5,
      "outcome": "consolidation",
      "converted": false,
      "watchlistTime": "2025-08-01T00:27:23.384Z",
      "lifetimeMinutes": 0,
      "createdAt": "2025-08-01T00:27:37.203Z"
    },
    {
      "symbol": "DENT/USDT",
      "anomalyId": "DENT_1754008049208",
      "tradeType": "Long",
      "volumeLeverage": 10.7,
      "outcome": "consolidation",
      "converted": false,
      "watchlistTime": "2025-08-01T00:27:29.208Z",
      "lifetimeMinutes": 0,
      "createdAt": "2025-08-01T00:27:37.205Z"
    },
    {
      "symbol": "JOE/USDT",
      "anomalyId": "JOE_1754008053532",
      "tradeType": "Long",
      "volumeLeverage": 8.2,
      "outcome": "consolidation",
      "converted": false,
      "watchlistTime": "2025-08-01T00:27:33.532Z",
      "lifetimeMinutes": 0,
      "createdAt": "2025-08-01T00:27:37.206Z"
    },
    {
      "symbol": "MBL/USDT",
      "anomalyId": "MBL_1754008074076",
      "tradeType": "Short",
      "volumeLeverage": 8.6,
      "outcome": "consolidation",
      "converted": false,
      "watchlistTime": "2025-08-01T00:27:54.076Z",
      "lifetimeMinutes": 0,
      "createdAt": "2025-08-01T00:28:07.064Z"
    },
    {
      "symbol": "JOE/USDT",
      "anomalyId": "JOE_1754008074081",
      "tradeType": "Long",
      "volumeLeverage": 8.2,
      "outcome": "consolidation",
      "converted": false,
      "watchlistTime": "2025-08-01T00:27:54.081Z",
      "lifetimeMinutes": 0,
      "createdAt": "2025-08-01T00:28:07.252Z"
    },
    {
      "symbol": "HOOK/USDT",
      "anomalyId": "HOOK_1754008101256",
      "tradeType": "Long",
      "volumeLeverage": 9.1,
      "outcome": "consolidation",
      "converted": false,
      "watchlistTime": "2025-08-01T00:28:21.256Z",
      "lifetimeMinutes": 0,
      "createdAt": "2025-08-01T00:28:37.027Z"
    },
    {
      "symbol": "ATA/USDT",
      "anomalyId": "ATA_1754008104506",
      "tradeType": "Long",
      "volumeLeverage": 9.4,
      "outcome": "consolidation",
      "converted": false,
      "watchlistTime": "2025-08-01T00:28:24.506Z",
      "lifetimeMinutes": 0,
      "createdAt": "2025-08-01T00:28:37.232Z"
    },
    {
      "symbol": "POLYX/USDT",
      "anomalyId": "POLYX_1754008311324",
      "tradeType": "Long",
      "volumeLeverage": 9,
      "outcome": "consolidation",
      "converted": false,
      "watchlistTime": "2025-08-01T00:31:51.324Z",
      "lifetimeMinutes": 0,
      "createdAt": "2025-08-01T00:32:07.086Z"
    },
    {
      "symbol": "ACE/USDT",
      "anomalyId": "ACE_1754008383947",
      "tradeType": "Long",
      "volumeLeverage": 70.7,
      "outcome": "consolidation",
      "converted": false,
      "watchlistTime": "2025-08-01T00:33:03.947Z",
      "lifetimeMinutes": 0,
      "createdAt": "2025-08-01T00:33:07.102Z"
    },
    {
      "symbol": "POLYX/USDT",
      "anomalyId": "POLYX_1754008611158",
      "tradeType": "Long",
      "volumeLeverage": 9,
      "outcome": "consolidation",
      "converted": false,
      "watchlistTime": "2025-08-01T00:36:51.158Z",
      "lifetimeMinutes": 0,
      "createdAt": "2025-08-01T00:37:07.188Z"
    },
    {
      "symbol": "ACE/USDT",
      "anomalyId": "ACE_1754008683570",
      "tradeType": "Long",
      "volumeLeverage": 70.7,
      "outcome": "consolidation",
      "converted": false,
      "watchlistTime": "2025-08-01T00:38:03.570Z",
      "lifetimeMinutes": 0,
      "createdAt": "2025-08-01T00:38:07.162Z"
    },
    {
      "symbol": "POLYX/USDT",
      "anomalyId": "POLYX_1754008911021",
      "tradeType": "Long",
      "volumeLeverage": 9,
      "outcome": "consolidation",
      "converted": false,
      "watchlistTime": "2025-08-01T00:41:51.021Z",
      "lifetimeMinutes": 0,
      "createdAt": "2025-08-01T00:42:07.219Z"
    },
    {
      "symbol": "ACE/USDT",
      "anomalyId": "ACE_1754008984960",
      "tradeType": "Long",
      "volumeLeverage": 70.7,
      "outcome": "consolidation",
      "converted": false,
      "watchlistTime": "2025-08-01T00:43:04.960Z",
      "lifetimeMinutes": 0,
      "createdAt": "2025-08-01T00:43:07.248Z"
    },
    {
      "symbol": "HOT/USDT",
      "anomalyId": "HOT_1754009209553",
      "tradeType": "Long",
      "volumeLeverage": 8.2,
      "outcome": "consolidation",
      "converted": false,
      "watchlistTime": "2025-08-01T00:46:49.553Z",
      "lifetimeMinutes": 0,
      "createdAt": "2025-08-01T00:47:07.273Z"
    },
    {
      "symbol": "MDT/USDT",
      "anomalyId": "MDT_1754009325057",
      "tradeType": "Short",
      "volumeLeverage": 8.9,
      "outcome": "consolidation",
      "converted": false,
      "watchlistTime": "2025-08-01T00:48:45.057Z",
      "lifetimeMinutes": 0,
      "createdAt": "2025-08-01T00:49:07.313Z"
    },
    {
      "symbol": "HOT/USDT",
      "anomalyId": "HOT_1754009508992",
      "tradeType": "Long",
      "volumeLeverage": 8.2,
      "outcome": "consolidation",
      "converted": false,
      "watchlistTime": "2025-08-01T00:51:48.992Z",
      "lifetimeMinutes": 0,
      "createdAt": "2025-08-01T00:52:07.355Z"
    },
    {
      "symbol": "MDT/USDT",
      "anomalyId": "MDT_1754009623799",
      "tradeType": "Short",
      "volumeLeverage": 8.9,
      "outcome": "consolidation",
      "converted": false,
      "watchlistTime": "2025-08-01T00:53:43.799Z",
      "lifetimeMinutes": 0,
      "createdAt": "2025-08-01T00:54:07.349Z"
    },
    {
      "symbol": "HOT/USDT",
      "anomalyId": "HOT_1754009808510",
      "tradeType": "Long",
      "volumeLeverage": 8.2,
      "outcome": "consolidation",
      "converted": false,
      "watchlistTime": "2025-08-01T00:56:48.510Z",
      "lifetimeMinutes": 0,
      "createdAt": "2025-08-01T00:57:07.398Z"
    },
    {
      "symbol": "MDT/USDT",
      "anomalyId": "MDT_1754009923440",
      "tradeType": "Short",
      "volumeLeverage": 8.9,
      "outcome": "consolidation",
      "converted": false,
      "watchlistTime": "2025-08-01T00:58:43.440Z",
      "lifetimeMinutes": 0,
      "createdAt": "2025-08-01T00:59:07.435Z"
    },
    {
      "symbol": "SHIB/USDT",
      "anomalyId": "SHIB_1754010068210",
      "tradeType": "Long",
      "volumeLeverage": 10.1,
      "outcome": "consolidation",
      "converted": false,
      "watchlistTime": "2025-08-01T01:01:08.210Z",
      "lifetimeMinutes": 0,
      "createdAt": "2025-08-01T01:01:37.501Z"
    },
    {
      "symbol": "PHA/USDT",
      "anomalyId": "PHA_1754010139848",
      "tradeType": "Long",
      "volumeLeverage": 15,
      "outcome": "consolidation",
      "converted": false,
      "watchlistTime": "2025-08-01T01:02:19.848Z",
      "lifetimeMinutes": 0,
      "createdAt": "2025-08-01T01:02:37.483Z"
    },
    {
      "symbol": "WAXP/USDT",
      "anomalyId": "WAXP_1754010147076",
      "tradeType": "Long",
      "volumeLeverage": 8.8,
      "outcome": "consolidation",
      "converted": false,
      "watchlistTime": "2025-08-01T01:02:27.076Z",
      "lifetimeMinutes": 0,
      "createdAt": "2025-08-01T01:02:37.666Z"
    },
    {
      "symbol": "SHIB/USDT",
      "anomalyId": "SHIB_1754010367782",
      "tradeType": "Long",
      "volumeLeverage": 10.1,
      "outcome": "consolidation",
      "converted": false,
      "watchlistTime": "2025-08-01T01:06:07.782Z",
      "lifetimeMinutes": 0,
      "createdAt": "2025-08-01T01:06:37.570Z"
    },
    {
      "symbol": "PHA/USDT",
      "anomalyId": "PHA_1754010438878",
      "tradeType": "Long",
      "volumeLeverage": 15,
      "outcome": "consolidation",
      "converted": false,
      "watchlistTime": "2025-08-01T01:07:18.878Z",
      "lifetimeMinutes": 0,
      "createdAt": "2025-08-01T01:07:37.566Z"
    },
    {
      "symbol": "WAXP/USDT",
      "anomalyId": "WAXP_1754010446549",
      "tradeType": "Long",
      "volumeLeverage": 8.8,
      "outcome": "consolidation",
      "converted": false,
      "watchlistTime": "2025-08-01T01:07:26.549Z",
      "lifetimeMinutes": 0,
      "createdAt": "2025-08-01T01:07:37.749Z"
    },
    {
      "symbol": "SHIB/USDT",
      "anomalyId": "SHIB_1754010668140",
      "tradeType": "Long",
      "volumeLeverage": 10.1,
      "outcome": "consolidation",
      "converted": false,
      "watchlistTime": "2025-08-01T01:11:08.140Z",
      "lifetimeMinutes": 0,
      "createdAt": "2025-08-01T01:11:37.660Z"
    },
    {
      "symbol": "PHA/USDT",
      "anomalyId": "PHA_1754010738682",
      "tradeType": "Long",
      "volumeLeverage": 15,
      "outcome": "consolidation",
      "converted": false,
      "watchlistTime": "2025-08-01T01:12:18.682Z",
      "lifetimeMinutes": 0,
      "createdAt": "2025-08-01T01:12:37.697Z"
    },
    {
      "symbol": "WAXP/USDT",
      "anomalyId": "WAXP_1754010746310",
      "tradeType": "Long",
      "volumeLeverage": 8.8,
      "outcome": "consolidation",
      "converted": false,
      "watchlistTime": "2025-08-01T01:12:26.310Z",
      "lifetimeMinutes": 0,
      "createdAt": "2025-08-01T01:12:37.888Z"
    },
    {
      "symbol": "GHST/USDT",
      "anomalyId": "GHST_1754011112672",
      "tradeType": "Short",
      "volumeLeverage": 12.6,
      "outcome": "consolidation",
      "converted": false,
      "watchlistTime": "2025-08-01T01:18:32.672Z",
      "lifetimeMinutes": 0,
      "createdAt": "2025-08-01T01:18:37.704Z"
    },
    {
      "symbol": "GHST/USDT",
      "anomalyId": "GHST_1754011412896",
      "tradeType": "Short",
      "volumeLeverage": 12.6,
      "outcome": "consolidation",
      "converted": false,
      "watchlistTime": "2025-08-01T01:23:32.896Z",
      "lifetimeMinutes": 0,
      "createdAt": "2025-08-01T01:23:37.789Z"
    },
    {
      "symbol": "GHST/USDT",
      "anomalyId": "GHST_1754011710373",
      "tradeType": "Short",
      "volumeLeverage": 12.6,
      "outcome": "consolidation",
      "converted": false,
      "watchlistTime": "2025-08-01T01:28:30.373Z",
      "lifetimeMinutes": 0,
      "createdAt": "2025-08-01T01:28:37.890Z"
    },
    {
      "symbol": "CKB/USDT",
      "anomalyId": "CKB_1754013698895",
      "tradeType": "Short",
      "volumeLeverage": 10.2,
      "outcome": "consolidation",
      "converted": false,
      "watchlistTime": "2025-08-01T02:01:38.895Z",
      "lifetimeMinutes": 0,
      "createdAt": "2025-08-01T02:02:08.418Z"
    },
    {
      "symbol": "GPS/USDT",
      "anomalyId": "GPS_1754013765778",
      "tradeType": "Short",
      "volumeLeverage": 12.2,
      "outcome": "consolidation",
      "converted": false,
      "watchlistTime": "2025-08-01T02:02:45.778Z",
      "lifetimeMinutes": 0,
      "createdAt": "2025-08-01T02:03:08.437Z"
    },
    {
      "symbol": "CKB/USDT",
      "anomalyId": "CKB_1754013999084",
      "tradeType": "Short",
      "volumeLeverage": 10.2,
      "outcome": "consolidation",
      "converted": false,
      "watchlistTime": "2025-08-01T02:06:39.084Z",
      "lifetimeMinutes": 0,
      "createdAt": "2025-08-01T02:07:08.513Z"
    },
    {
      "symbol": "GPS/USDT",
      "anomalyId": "GPS_1754014063509",
      "tradeType": "Short",
      "volumeLeverage": 12.2,
      "outcome": "consolidation",
      "converted": false,
      "watchlistTime": "2025-08-01T02:07:43.509Z",
      "lifetimeMinutes": 0,
      "createdAt": "2025-08-01T02:08:08.523Z"
    },
    {
      "symbol": "CKB/USDT",
      "anomalyId": "CKB_1754014300137",
      "tradeType": "Short",
      "volumeLeverage": 10.2,
      "outcome": "consolidation",
      "converted": false,
      "watchlistTime": "2025-08-01T02:11:40.137Z",
      "lifetimeMinutes": 0,
      "createdAt": "2025-08-01T02:12:08.596Z"
    },
    {
      "symbol": "GPS/USDT",
      "anomalyId": "GPS_1754014365716",
      "tradeType": "Short",
      "volumeLeverage": 12.2,
      "outcome": "consolidation",
      "converted": false,
      "watchlistTime": "2025-08-01T02:12:45.716Z",
      "lifetimeMinutes": 0,
      "createdAt": "2025-08-01T02:13:08.605Z"
    },
    {
      "symbol": "BCH/USDT",
      "anomalyId": "BCH_1754019066593",
      "tradeType": "Short",
      "volumeLeverage": 11.5,
      "outcome": "consolidation",
      "converted": false,
      "watchlistTime": "2025-08-01T03:31:06.593Z",
      "lifetimeMinutes": 0,
      "createdAt": "2025-08-01T03:31:09.905Z"
    },
    {
      "symbol": "BCH/USDT",
      "anomalyId": "BCH_1754019366600",
      "tradeType": "Short",
      "volumeLeverage": 11.5,
      "outcome": "consolidation",
      "converted": false,
      "watchlistTime": "2025-08-01T03:36:06.600Z",
      "lifetimeMinutes": 0,
      "createdAt": "2025-08-01T03:36:10.119Z"
    },
    {
      "symbol": "BCH/USDT",
      "anomalyId": "BCH_1754019666614",
      "tradeType": "Short",
      "volumeLeverage": 11.5,
      "outcome": "consolidation",
      "converted": false,
      "watchlistTime": "2025-08-01T03:41:06.614Z",
      "lifetimeMinutes": 0,
      "createdAt": "2025-08-01T03:41:10.058Z"
    },
    {
      "symbol": "PLUME/USDT",
      "anomalyId": "PLUME_1754020001530",
      "tradeType": "Short",
      "volumeLeverage": 8.9,
      "outcome": "consolidation",
      "converted": false,
      "watchlistTime": "2025-08-01T03:46:41.530Z",
      "lifetimeMinutes": 0,
      "createdAt": "2025-08-01T03:47:10.136Z"
    },
    {
      "symbol": "SHIB/USDT",
      "anomalyId": "SHIB_1754019068031",
      "tradeType": "Short",
      "volumeLeverage": 8.4,
      "outcome": "entry",
      "converted": true,
      "watchlistTime": "2025-08-01T03:31:08.031Z",
      "lifetimeMinutes": 17,
      "createdAt": "2025-08-01T03:48:10.125Z"
    },
    {
      "symbol": "PLUME/USDT",
      "anomalyId": "PLUME_1754020302803",
      "tradeType": "Short",
      "volumeLeverage": 8.9,
      "outcome": "consolidation",
      "converted": false,
      "watchlistTime": "2025-08-01T03:51:42.803Z",
      "lifetimeMinutes": 0,
      "createdAt": "2025-08-01T03:52:10.646Z"
    },
    {
      "symbol": "PLUME/USDT",
      "anomalyId": "PLUME_1754020602292",
      "tradeType": "Short",
      "volumeLeverage": 8.9,
      "outcome": "consolidation",
      "converted": false,
      "watchlistTime": "2025-08-01T03:56:42.292Z",
      "lifetimeMinutes": 0,
      "createdAt": "2025-08-01T03:57:10.863Z"
    },
    {
      "symbol": "ETHW/USDT",
      "anomalyId": "ETHW_1754021808057",
      "tradeType": "Long",
      "volumeLeverage": 15.6,
      "outcome": "consolidation",
      "converted": false,
      "watchlistTime": "2025-08-01T04:16:48.057Z",
      "lifetimeMinutes": 0,
      "createdAt": "2025-08-01T04:17:11.017Z"
    },
    {
      "symbol": "VVV/USDT",
      "anomalyId": "VVV_1754021832721",
      "tradeType": "Long",
      "volumeLeverage": 9.6,
      "outcome": "consolidation",
      "converted": false,
      "watchlistTime": "2025-08-01T04:17:12.721Z",
      "lifetimeMinutes": 0,
      "createdAt": "2025-08-01T04:17:41.031Z"
    },
    {
      "symbol": "NIL/USDT",
      "anomalyId": "NIL_1754021854378",
      "tradeType": "Long",
      "volumeLeverage": 9.8,
      "outcome": "consolidation",
      "converted": false,
      "watchlistTime": "2025-08-01T04:17:34.378Z",
      "lifetimeMinutes": 0,
      "createdAt": "2025-08-01T04:17:41.208Z"
    },
    {
      "symbol": "ETHW/USDT",
      "anomalyId": "ETHW_1754022106683",
      "tradeType": "Long",
      "volumeLeverage": 15.6,
      "outcome": "consolidation",
      "converted": false,
      "watchlistTime": "2025-08-01T04:21:46.683Z",
      "lifetimeMinutes": 0,
      "createdAt": "2025-08-01T04:22:11.113Z"
    },
    {
      "symbol": "VVV/USDT",
      "anomalyId": "VVV_1754022131599",
      "tradeType": "Long",
      "volumeLeverage": 9.6,
      "outcome": "consolidation",
      "converted": false,
      "watchlistTime": "2025-08-01T04:22:11.599Z",
      "lifetimeMinutes": 0,
      "createdAt": "2025-08-01T04:22:41.064Z"
    },
    {
      "symbol": "NIL/USDT",
      "anomalyId": "NIL_1754022151886",
      "tradeType": "Long",
      "volumeLeverage": 9.8,
      "outcome": "consolidation",
      "converted": false,
      "watchlistTime": "2025-08-01T04:22:31.886Z",
      "lifetimeMinutes": 0,
      "createdAt": "2025-08-01T04:22:41.248Z"
    },
    {
      "symbol": "ETHW/USDT",
      "anomalyId": "ETHW_1754022407430",
      "tradeType": "Long",
      "volumeLeverage": 15.6,
      "outcome": "consolidation",
      "converted": false,
      "watchlistTime": "2025-08-01T04:26:47.430Z",
      "lifetimeMinutes": 0,
      "createdAt": "2025-08-01T04:27:11.151Z"
    },
    {
      "symbol": "VVV/USDT",
      "anomalyId": "VVV_1754022433231",
      "tradeType": "Long",
      "volumeLeverage": 9.6,
      "outcome": "consolidation",
      "converted": false,
      "watchlistTime": "2025-08-01T04:27:13.231Z",
      "lifetimeMinutes": 0,
      "createdAt": "2025-08-01T04:27:41.310Z"
    },
    {
      "symbol": "NIL/USDT",
      "anomalyId": "NIL_1754022454050",
      "tradeType": "Long",
      "volumeLeverage": 9.8,
      "outcome": "consolidation",
      "converted": false,
      "watchlistTime": "2025-08-01T04:27:34.050Z",
      "lifetimeMinutes": 0,
      "createdAt": "2025-08-01T04:27:41.492Z"
    },
    {
      "symbol": "WIN/USDT",
      "anomalyId": "WIN_1754022753191",
      "tradeType": "Short",
      "volumeLeverage": 11.2,
      "outcome": "consolidation",
      "converted": false,
      "watchlistTime": "2025-08-01T04:32:33.191Z",
      "lifetimeMinutes": 0,
      "createdAt": "2025-08-01T04:32:40.779Z"
    },
    {
      "symbol": "WIN/USDT",
      "anomalyId": "WIN_1754023055198",
      "tradeType": "Short",
      "volumeLeverage": 11.2,
      "outcome": "consolidation",
      "converted": false,
      "watchlistTime": "2025-08-01T04:37:35.198Z",
      "lifetimeMinutes": 0,
      "createdAt": "2025-08-01T04:37:40.963Z"
    },
    {
      "symbol": "WIN/USDT",
      "anomalyId": "WIN_1754023357249",
      "tradeType": "Short",
      "volumeLeverage": 11.2,
      "outcome": "consolidation",
      "converted": false,
      "watchlistTime": "2025-08-01T04:42:37.249Z",
      "lifetimeMinutes": 0,
      "createdAt": "2025-08-01T04:42:41.420Z"
    },
    {
      "symbol": "ASTR/USDT",
      "anomalyId": "ASTR_1754022705582",
      "tradeType": "Long",
      "volumeLeverage": 13.8,
      "outcome": "entry",
      "converted": true,
      "watchlistTime": "2025-08-01T04:31:45.582Z",
      "lifetimeMinutes": 13,
      "createdAt": "2025-08-01T04:45:10.960Z"
    },
    {
      "symbol": "SAHARA/USDT",
      "anomalyId": "SAHARA_1754025413114",
      "tradeType": "Short",
      "volumeLeverage": 9.5,
      "outcome": "consolidation",
      "converted": false,
      "watchlistTime": "2025-08-01T05:16:53.114Z",
      "lifetimeMinutes": 0,
      "createdAt": "2025-08-01T05:17:12.164Z"
    },
    {
      "symbol": "MOVR/USDT",
      "anomalyId": "MOVR_1754025462206",
      "tradeType": "Long",
      "volumeLeverage": 33.1,
      "outcome": "consolidation",
      "converted": false,
      "watchlistTime": "2025-08-01T05:17:42.206Z",
      "lifetimeMinutes": 0,
      "createdAt": "2025-08-01T05:18:12.201Z"
    },
    {
      "symbol": "SAHARA/USDT",
      "anomalyId": "SAHARA_1754025711363",
      "tradeType": "Short",
      "volumeLeverage": 9.5,
      "outcome": "consolidation",
      "converted": false,
      "watchlistTime": "2025-08-01T05:21:51.363Z",
      "lifetimeMinutes": 0,
      "createdAt": "2025-08-01T05:22:12.176Z"
    },
    {
      "symbol": "MOVR/USDT",
      "anomalyId": "MOVR_1754025759144",
      "tradeType": "Long",
      "volumeLeverage": 33.1,
      "outcome": "consolidation",
      "converted": false,
      "watchlistTime": "2025-08-01T05:22:39.144Z",
      "lifetimeMinutes": 0,
      "createdAt": "2025-08-01T05:22:42.176Z"
    },
    {
      "symbol": "SAHARA/USDT",
      "anomalyId": "SAHARA_1754026012796",
      "tradeType": "Short",
      "volumeLeverage": 9.5,
      "outcome": "consolidation",
      "converted": false,
      "watchlistTime": "2025-08-01T05:26:52.796Z",
      "lifetimeMinutes": 0,
      "createdAt": "2025-08-01T05:27:12.161Z"
    },
    {
      "symbol": "MOVR/USDT",
      "anomalyId": "MOVR_1754026062876",
      "tradeType": "Long",
      "volumeLeverage": 33.1,
      "outcome": "consolidation",
      "converted": false,
      "watchlistTime": "2025-08-01T05:27:42.876Z",
      "lifetimeMinutes": 0,
      "createdAt": "2025-08-01T05:28:12.159Z"
    },
    {
      "symbol": "HOME/USDT",
      "anomalyId": "HOME_1754026332599",
      "tradeType": "Long",
      "volumeLeverage": 9.5,
      "outcome": "consolidation",
      "converted": false,
      "watchlistTime": "2025-08-01T05:32:12.599Z",
      "lifetimeMinutes": 0,
      "createdAt": "2025-08-01T05:32:41.692Z"
    },
    {
      "symbol": "HOME/USDT",
      "anomalyId": "HOME_1754026636301",
      "tradeType": "Long",
      "volumeLeverage": 9.5,
      "outcome": "consolidation",
      "converted": false,
      "watchlistTime": "2025-08-01T05:37:16.301Z",
      "lifetimeMinutes": 0,
      "createdAt": "2025-08-01T05:37:41.790Z"
    },
    {
      "symbol": "HOME/USDT",
      "anomalyId": "HOME_1754026934775",
      "tradeType": "Long",
      "volumeLeverage": 9.5,
      "outcome": "consolidation",
      "converted": false,
      "watchlistTime": "2025-08-01T05:42:14.775Z",
      "lifetimeMinutes": 0,
      "createdAt": "2025-08-01T05:42:41.884Z"
    },
    {
      "symbol": "STORJ/USDT",
      "anomalyId": "STORJ_1754024580057",
      "tradeType": "Long",
      "volumeLeverage": 10.9,
      "outcome": "cancel",
      "converted": false,
      "watchlistTime": "2025-08-01T05:03:00.057Z",
      "lifetimeMinutes": 42,
      "createdAt": "2025-08-01T05:45:12.010Z"
    },
    {
      "symbol": "MLN/USDT",
      "anomalyId": "MLN_1754023715154",
      "tradeType": "Long",
      "volumeLeverage": 16.6,
      "outcome": "cancel",
      "converted": false,
      "watchlistTime": "2025-08-01T04:48:35.154Z",
      "lifetimeMinutes": 59,
      "createdAt": "2025-08-01T05:47:12.029Z"
    },
    {
      "symbol": "WBETH/USDT",
      "anomalyId": "WBETH_1754022666652",
      "tradeType": "Long",
      "volumeLeverage": 9.2,
      "outcome": "timeout",
      "converted": false,
      "watchlistTime": "2025-08-01T04:31:06.652Z",
      "lifetimeMinutes": 90,
      "createdAt": "2025-08-01T06:01:12.331Z"
    },
    {
      "symbol": "IOTX/USDT",
      "anomalyId": "IOTX_1754028108480",
      "tradeType": "Long",
      "volumeLeverage": 10.6,
      "outcome": "consolidation",
      "converted": false,
      "watchlistTime": "2025-08-01T06:01:48.480Z",
      "lifetimeMinutes": 0,
      "createdAt": "2025-08-01T06:02:12.238Z"
    },
    {
      "symbol": "IOTX/USDT",
      "anomalyId": "IOTX_1754028409724",
      "tradeType": "Long",
      "volumeLeverage": 10.6,
      "outcome": "consolidation",
      "converted": false,
      "watchlistTime": "2025-08-01T06:06:49.724Z",
      "lifetimeMinutes": 0,
      "createdAt": "2025-08-01T06:07:12.217Z"
    },
    {
      "symbol": "IOTX/USDT",
      "anomalyId": "IOTX_1754028706425",
      "tradeType": "Long",
      "volumeLeverage": 10.6,
      "outcome": "consolidation",
      "converted": false,
      "watchlistTime": "2025-08-01T06:11:46.425Z",
      "lifetimeMinutes": 0,
      "createdAt": "2025-08-01T06:12:12.299Z"
    },
    {
      "symbol": "PUFFER/USDT",
      "anomalyId": "PUFFER_1754029096975",
      "tradeType": "Long",
      "volumeLeverage": 10.2,
      "outcome": "consolidation",
      "converted": false,
      "watchlistTime": "2025-08-01T06:18:16.975Z",
      "lifetimeMinutes": 0,
      "createdAt": "2025-08-01T06:18:42.402Z"
    },
    {
      "symbol": "PUFFER/USDT",
      "anomalyId": "PUFFER_1754029395979",
      "tradeType": "Long",
      "volumeLeverage": 10.2,
      "outcome": "consolidation",
      "converted": false,
      "watchlistTime": "2025-08-01T06:23:15.979Z",
      "lifetimeMinutes": 0,
      "createdAt": "2025-08-01T06:23:42.478Z"
    },
    {
      "symbol": "PUFFER/USDT",
      "anomalyId": "PUFFER_1754029702191",
      "tradeType": "Long",
      "volumeLeverage": 10.2,
      "outcome": "consolidation",
      "converted": false,
      "watchlistTime": "2025-08-01T06:28:22.191Z",
      "lifetimeMinutes": 0,
      "createdAt": "2025-08-01T06:28:42.533Z"
    },
    {
      "symbol": "LA/USDT",
      "anomalyId": "LA_1754029958137",
      "tradeType": "Long",
      "volumeLeverage": 19.8,
      "outcome": "consolidation",
      "converted": false,
      "watchlistTime": "2025-08-01T06:32:38.137Z",
      "lifetimeMinutes": 0,
      "createdAt": "2025-08-01T06:32:42.828Z"
    },
    {
      "symbol": "LA/USDT",
      "anomalyId": "LA_1754030263790",
      "tradeType": "Long",
      "volumeLeverage": 19.8,
      "outcome": "consolidation",
      "converted": false,
      "watchlistTime": "2025-08-01T06:37:43.790Z",
      "lifetimeMinutes": 0,
      "createdAt": "2025-08-01T06:38:13.012Z"
    },
    {
      "symbol": "LA/USDT",
      "anomalyId": "LA_1754030556330",
      "tradeType": "Long",
      "volumeLeverage": 19.8,
      "outcome": "consolidation",
      "converted": false,
      "watchlistTime": "2025-08-01T06:42:36.330Z",
      "lifetimeMinutes": 0,
      "createdAt": "2025-08-01T06:42:42.746Z"
    },
    {
      "symbol": "FUN/USDT",
      "anomalyId": "FUN_1754031734966",
      "tradeType": "Short",
      "volumeLeverage": 11,
      "outcome": "consolidation",
      "converted": false,
      "watchlistTime": "2025-08-01T07:02:14.966Z",
      "lifetimeMinutes": 0,
      "createdAt": "2025-08-01T07:02:43.676Z"
    },
    {
      "symbol": "FUN/USDT",
      "anomalyId": "FUN_1754032027614",
      "tradeType": "Short",
      "volumeLeverage": 11,
      "outcome": "consolidation",
      "converted": false,
      "watchlistTime": "2025-08-01T07:07:07.614Z",
      "lifetimeMinutes": 0,
      "createdAt": "2025-08-01T07:07:13.120Z"
    },
    {
      "symbol": "FUN/USDT",
      "anomalyId": "FUN_1754032332080",
      "tradeType": "Short",
      "volumeLeverage": 11,
      "outcome": "consolidation",
      "converted": false,
      "watchlistTime": "2025-08-01T07:12:12.080Z",
      "lifetimeMinutes": 0,
      "createdAt": "2025-08-01T07:12:13.210Z"
    },
    {
      "symbol": "BICO/USDT",
      "anomalyId": "BICO_1754032639858",
      "tradeType": "Long",
      "volumeLeverage": 11,
      "outcome": "consolidation",
      "converted": false,
      "watchlistTime": "2025-08-01T07:17:19.858Z",
      "lifetimeMinutes": 0,
      "createdAt": "2025-08-01T07:17:43.256Z"
    },
    {
      "symbol": "BICO/USDT",
      "anomalyId": "BICO_1754032948206",
      "tradeType": "Long",
      "volumeLeverage": 11,
      "outcome": "consolidation",
      "converted": false,
      "watchlistTime": "2025-08-01T07:22:28.206Z",
      "lifetimeMinutes": 0,
      "createdAt": "2025-08-01T07:22:43.386Z"
    },
    {
      "symbol": "BICO/USDT",
      "anomalyId": "BICO_1754033235728",
      "tradeType": "Long",
      "volumeLeverage": 11,
      "outcome": "consolidation",
      "converted": false,
      "watchlistTime": "2025-08-01T07:27:15.728Z",
      "lifetimeMinutes": 0,
      "createdAt": "2025-08-01T07:27:43.360Z"
    },
    {
      "symbol": "CTK/USDT",
      "anomalyId": "CTK_1754034513073",
      "tradeType": "Long",
      "volumeLeverage": 41.7,
      "outcome": "consolidation",
      "converted": false,
      "watchlistTime": "2025-08-01T07:48:33.073Z",
      "lifetimeMinutes": 0,
      "createdAt": "2025-08-01T07:48:45.499Z"
    },
    {
      "symbol": "CTK/USDT",
      "anomalyId": "CTK_1754034810196",
      "tradeType": "Long",
      "volumeLeverage": 41.7,
      "outcome": "consolidation",
      "converted": false,
      "watchlistTime": "2025-08-01T07:53:30.196Z",
      "lifetimeMinutes": 0,
      "createdAt": "2025-08-01T07:53:48.803Z"
    },
    {
      "symbol": "CTK/USDT",
      "anomalyId": "CTK_1754035119484",
      "tradeType": "Long",
      "volumeLeverage": 41.7,
      "outcome": "consolidation",
      "converted": false,
      "watchlistTime": "2025-08-01T07:58:39.484Z",
      "lifetimeMinutes": 0,
      "createdAt": "2025-08-01T07:58:43.925Z"
    },
    {
      "symbol": "OGN/USDT",
      "anomalyId": "OGN_1754034530366",
      "tradeType": "Long",
      "volumeLeverage": 9.9,
      "outcome": "cancel",
      "converted": false,
      "watchlistTime": "2025-08-01T07:48:50.366Z",
      "lifetimeMinutes": 11,
      "createdAt": "2025-08-01T08:00:14.115Z"
    },
    {
      "symbol": "FLOW/USDT",
      "anomalyId": "FLOW_1754036227163",
      "tradeType": "Long",
      "volumeLeverage": 10,
      "outcome": "consolidation",
      "converted": false,
      "watchlistTime": "2025-08-01T08:17:07.163Z",
      "lifetimeMinutes": 0,
      "createdAt": "2025-08-01T08:17:15.707Z"
    },
    {
      "symbol": "OM/USDT",
      "anomalyId": "OM_1754036256487",
      "tradeType": "Long",
      "volumeLeverage": 12.3,
      "outcome": "consolidation",
      "converted": false,
      "watchlistTime": "2025-08-01T08:17:36.487Z",
      "lifetimeMinutes": 0,
      "createdAt": "2025-08-01T08:17:45.089Z"
    },
    {
      "symbol": "TWT/USDT",
      "anomalyId": "TWT_1754036246918",
      "tradeType": "Long",
      "volumeLeverage": 8,
      "outcome": "consolidation",
      "converted": false,
      "watchlistTime": "2025-08-01T08:17:26.918Z",
      "lifetimeMinutes": 0,
      "createdAt": "2025-08-01T08:17:45.090Z"
    },
    {
      "symbol": "SNX/USDT",
      "anomalyId": "SNX_1754036260995",
      "tradeType": "Long",
      "volumeLeverage": 8.2,
      "outcome": "consolidation",
      "converted": false,
      "watchlistTime": "2025-08-01T08:17:40.995Z",
      "lifetimeMinutes": 0,
      "createdAt": "2025-08-01T08:17:45.091Z"
    },
    {
      "symbol": "TRB/USDT",
      "anomalyId": "TRB_1754036290991",
      "tradeType": "Long",
      "volumeLeverage": 10,
      "outcome": "consolidation",
      "converted": false,
      "watchlistTime": "2025-08-01T08:18:10.991Z",
      "lifetimeMinutes": 0,
      "createdAt": "2025-08-01T08:18:14.375Z"
    },
    {
      "symbol": "SIGN/USDT",
      "anomalyId": "SIGN_1754036298954",
      "tradeType": "Long",
      "volumeLeverage": 49.5,
      "outcome": "consolidation",
      "converted": false,
      "watchlistTime": "2025-08-01T08:18:18.954Z",
      "lifetimeMinutes": 0,
      "createdAt": "2025-08-01T08:18:44.142Z"
    },
    {
      "symbol": "C98/USDT",
      "anomalyId": "C98_1754036334699",
      "tradeType": "Long",
      "volumeLeverage": 8.5,
      "outcome": "consolidation",
      "converted": false,
      "watchlistTime": "2025-08-01T08:18:54.699Z",
      "lifetimeMinutes": 0,
      "createdAt": "2025-08-01T08:19:14.258Z"
    },
    {
      "symbol": "TLM/USDT",
      "anomalyId": "TLM_1754036383829",
      "tradeType": "Long",
      "volumeLeverage": 8.9,
      "outcome": "consolidation",
      "converted": false,
      "watchlistTime": "2025-08-01T08:19:43.829Z",
      "lifetimeMinutes": 1,
      "createdAt": "2025-08-01T08:20:14.269Z"
    },
    {
      "symbol": "ARPA/USDT",
      "anomalyId": "ARPA_1754036412386",
      "tradeType": "Long",
      "volumeLeverage": 9.6,
      "outcome": "consolidation",
      "converted": false,
      "watchlistTime": "2025-08-01T08:20:12.386Z",
      "lifetimeMinutes": 0,
      "createdAt": "2025-08-01T08:20:14.270Z"
    },
    {
      "symbol": "FLOW/USDT",
      "anomalyId": "FLOW_1754036486303",
      "tradeType": "Long",
      "volumeLeverage": 10,
      "outcome": "consolidation",
      "converted": false,
      "watchlistTime": "2025-08-01T08:21:26.303Z",
      "lifetimeMinutes": 0,
      "createdAt": "2025-08-01T08:21:45.912Z"
    },
    {
      "symbol": "OM/USDT",
      "anomalyId": "OM_1754036516259",
      "tradeType": "Long",
      "volumeLeverage": 12.3,
      "outcome": "consolidation",
      "converted": false,
      "watchlistTime": "2025-08-01T08:21:56.259Z",
      "lifetimeMinutes": 0,
      "createdAt": "2025-08-01T08:22:14.613Z"
    },
    {
      "symbol": "TWT/USDT",
      "anomalyId": "TWT_1754036505675",
      "tradeType": "Long",
      "volumeLeverage": 8,
      "outcome": "consolidation",
      "converted": false,
      "watchlistTime": "2025-08-01T08:21:45.675Z",
      "lifetimeMinutes": 0,
      "createdAt": "2025-08-01T08:22:14.616Z"
    },
    {
      "symbol": "SNX/USDT",
      "anomalyId": "SNX_1754036522064",
      "tradeType": "Long",
      "volumeLeverage": 8.2,
      "outcome": "consolidation",
      "converted": false,
      "watchlistTime": "2025-08-01T08:22:02.064Z",
      "lifetimeMinutes": 0,
      "createdAt": "2025-08-01T08:22:14.617Z"
    },
    {
      "symbol": "TRB/USDT",
      "anomalyId": "TRB_1754036547127",
      "tradeType": "Long",
      "volumeLeverage": 10,
      "outcome": "consolidation",
      "converted": false,
      "watchlistTime": "2025-08-01T08:22:27.127Z",
      "lifetimeMinutes": 0,
      "createdAt": "2025-08-01T08:22:44.955Z"
    },
    {
      "symbol": "SIGN/USDT",
      "anomalyId": "SIGN_1754036557018",
      "tradeType": "Long",
      "volumeLeverage": 49.5,
      "outcome": "consolidation",
      "converted": false,
      "watchlistTime": "2025-08-01T08:22:37.018Z",
      "lifetimeMinutes": 0,
      "createdAt": "2025-08-01T08:22:44.958Z"
    },
    {
      "symbol": "C98/USDT",
      "anomalyId": "C98_1754036596776",
      "tradeType": "Long",
      "volumeLeverage": 8.5,
      "outcome": "consolidation",
      "converted": false,
      "watchlistTime": "2025-08-01T08:23:16.776Z",
      "lifetimeMinutes": 0,
      "createdAt": "2025-08-01T08:23:44.525Z"
    },
    {
      "symbol": "TLM/USDT",
      "anomalyId": "TLM_1754036630939",
      "tradeType": "Long",
      "volumeLeverage": 8.9,
      "outcome": "consolidation",
      "converted": false,
      "watchlistTime": "2025-08-01T08:23:50.939Z",
      "lifetimeMinutes": 0,
      "createdAt": "2025-08-01T08:24:14.261Z"
    },
    {
      "symbol": "ARPA/USDT",
      "anomalyId": "ARPA_1754036658570",
      "tradeType": "Long",
      "volumeLeverage": 9.6,
      "outcome": "consolidation",
      "converted": false,
      "watchlistTime": "2025-08-01T08:24:18.570Z",
      "lifetimeMinutes": 0,
      "createdAt": "2025-08-01T08:24:22.436Z"
    },
    {
      "symbol": "FLOW/USDT",
      "anomalyId": "FLOW_1754036789028",
      "tradeType": "Long",
      "volumeLeverage": 10,
      "outcome": "consolidation",
      "converted": false,
      "watchlistTime": "2025-08-01T08:26:29.028Z",
      "lifetimeMinutes": 0,
      "createdAt": "2025-08-01T08:26:44.674Z"
    },
    {
      "symbol": "SNX/USDT",
      "anomalyId": "SNX_1754036820857",
      "tradeType": "Long",
      "volumeLeverage": 8.2,
      "outcome": "consolidation",
      "converted": false,
      "watchlistTime": "2025-08-01T08:27:00.857Z",
      "lifetimeMinutes": 0,
      "createdAt": "2025-08-01T08:27:14.641Z"
    },
    {
      "symbol": "OM/USDT",
      "anomalyId": "OM_1754036813430",
      "tradeType": "Long",
      "volumeLeverage": 12.3,
      "outcome": "consolidation",
      "converted": false,
      "watchlistTime": "2025-08-01T08:26:53.431Z",
      "lifetimeMinutes": 0,
      "createdAt": "2025-08-01T08:27:14.647Z"
    },
    {
      "symbol": "TWT/USDT",
      "anomalyId": "TWT_1754036804293",
      "tradeType": "Long",
      "volumeLeverage": 8,
      "outcome": "consolidation",
      "converted": false,
      "watchlistTime": "2025-08-01T08:26:44.293Z",
      "lifetimeMinutes": 1,
      "createdAt": "2025-08-01T08:27:14.651Z"
    },
    {
      "symbol": "TRB/USDT",
      "anomalyId": "TRB_1754036849268",
      "tradeType": "Long",
      "volumeLeverage": 10,
      "outcome": "consolidation",
      "converted": false,
      "watchlistTime": "2025-08-01T08:27:29.269Z",
      "lifetimeMinutes": 0,
      "createdAt": "2025-08-01T08:27:44.807Z"
    },
    {
      "symbol": "SIGN/USDT",
      "anomalyId": "SIGN_1754036858112",
      "tradeType": "Long",
      "volumeLeverage": 49.5,
      "outcome": "consolidation",
      "converted": false,
      "watchlistTime": "2025-08-01T08:27:38.112Z",
      "lifetimeMinutes": 0,
      "createdAt": "2025-08-01T08:27:44.810Z"
    },
    {
      "symbol": "C98/USDT",
      "anomalyId": "C98_1754036896333",
      "tradeType": "Long",
      "volumeLeverage": 8.5,
      "outcome": "consolidation",
      "converted": false,
      "watchlistTime": "2025-08-01T08:28:16.333Z",
      "lifetimeMinutes": 0,
      "createdAt": "2025-08-01T08:28:44.565Z"
    },
    {
      "symbol": "TLM/USDT",
      "anomalyId": "TLM_1754036946392",
      "tradeType": "Long",
      "volumeLeverage": 8.9,
      "outcome": "consolidation",
      "converted": false,
      "watchlistTime": "2025-08-01T08:29:06.392Z",
      "lifetimeMinutes": 0,
      "createdAt": "2025-08-01T08:29:14.780Z"
    },
    {
      "symbol": "STG/USDT",
      "anomalyId": "STG_1754036271655",
      "tradeType": "Long",
      "volumeLeverage": 21,
      "outcome": "entry",
      "converted": true,
      "watchlistTime": "2025-08-01T08:17:51.655Z",
      "lifetimeMinutes": 21,
      "createdAt": "2025-08-01T08:38:44.686Z"
    },
    {
      "symbol": "CVC/USDT",
      "anomalyId": "CVC_1754036308925",
      "tradeType": "Long",
      "volumeLeverage": 12.5,
      "outcome": "entry",
      "converted": true,
      "watchlistTime": "2025-08-01T08:18:28.925Z",
      "lifetimeMinutes": 27,
      "createdAt": "2025-08-01T08:45:15.500Z"
    },
    {
      "symbol": "GRT/USDT",
      "anomalyId": "GRT_1754037082471",
      "tradeType": "Long",
      "volumeLeverage": 8.3,
      "outcome": "entry",
      "converted": true,
      "watchlistTime": "2025-08-01T08:31:22.471Z",
      "lifetimeMinutes": 14,
      "createdAt": "2025-08-01T08:45:15.512Z"
    },
    {
      "symbol": "CYBER/USDT",
      "anomalyId": "CYBER_1754042545685",
      "tradeType": "Long",
      "volumeLeverage": 8.6,
      "outcome": "consolidation",
      "converted": false,
      "watchlistTime": "2025-08-01T10:02:25.685Z",
      "lifetimeMinutes": 0,
      "createdAt": "2025-08-01T10:02:46.360Z"
    },
    {
      "symbol": "CYBER/USDT",
      "anomalyId": "CYBER_1754042845821",
      "tradeType": "Long",
      "volumeLeverage": 8.6,
      "outcome": "consolidation",
      "converted": false,
      "watchlistTime": "2025-08-01T10:07:25.821Z",
      "lifetimeMinutes": 0,
      "createdAt": "2025-08-01T10:07:46.414Z"
    },
    {
      "symbol": "CYBER/USDT",
      "anomalyId": "CYBER_1754043144289",
      "tradeType": "Long",
      "volumeLeverage": 8.6,
      "outcome": "consolidation",
      "converted": false,
      "watchlistTime": "2025-08-01T10:12:24.289Z",
      "lifetimeMinutes": 0,
      "createdAt": "2025-08-01T10:12:46.527Z"
    },
    {
      "symbol": "LQTY/USDT",
      "anomalyId": "LQTY_1754043474279",
      "tradeType": "Short",
      "volumeLeverage": 10.7,
      "outcome": "consolidation",
      "converted": false,
      "watchlistTime": "2025-08-01T10:17:54.279Z",
      "lifetimeMinutes": 0,
      "createdAt": "2025-08-01T10:18:16.396Z"
    },
    {
      "symbol": "GNS/USDT",
      "anomalyId": "GNS_1754043549705",
      "tradeType": "Long",
      "volumeLeverage": 11.1,
      "outcome": "consolidation",
      "converted": false,
      "watchlistTime": "2025-08-01T10:19:09.705Z",
      "lifetimeMinutes": 0,
      "createdAt": "2025-08-01T10:19:18.288Z"
    },
    {
      "symbol": "LQTY/USDT",
      "anomalyId": "LQTY_1754043745811",
      "tradeType": "Short",
      "volumeLeverage": 10.7,
      "outcome": "consolidation",
      "converted": false,
      "watchlistTime": "2025-08-01T10:22:25.811Z",
      "lifetimeMinutes": 0,
      "createdAt": "2025-08-01T10:22:46.212Z"
    },
    {
      "symbol": "GNS/USDT",
      "anomalyId": "GNS_1754043785986",
      "tradeType": "Long",
      "volumeLeverage": 11.1,
      "outcome": "consolidation",
      "converted": false,
      "watchlistTime": "2025-08-01T10:23:05.986Z",
      "lifetimeMinutes": 0,
      "createdAt": "2025-08-01T10:23:16.472Z"
    },
    {
      "symbol": "LQTY/USDT",
      "anomalyId": "LQTY_1754044053773",
      "tradeType": "Short",
      "volumeLeverage": 10.7,
      "outcome": "consolidation",
      "converted": false,
      "watchlistTime": "2025-08-01T10:27:33.773Z",
      "lifetimeMinutes": 0,
      "createdAt": "2025-08-01T10:27:46.410Z"
    },
    {
      "symbol": "GNS/USDT",
      "anomalyId": "GNS_1754044091566",
      "tradeType": "Long",
      "volumeLeverage": 11.1,
      "outcome": "consolidation",
      "converted": false,
      "watchlistTime": "2025-08-01T10:28:11.566Z",
      "lifetimeMinutes": 0,
      "createdAt": "2025-08-01T10:28:16.321Z"
    },
    {
      "symbol": "VVV/USDT",
      "anomalyId": "VVV_1754044361329",
      "tradeType": "Long",
      "volumeLeverage": 11.9,
      "outcome": "consolidation",
      "converted": false,
      "watchlistTime": "2025-08-01T10:32:41.329Z",
      "lifetimeMinutes": 0,
      "createdAt": "2025-08-01T10:32:46.615Z"
    },
    {
      "symbol": "VVV/USDT",
      "anomalyId": "VVV_1754044673657",
      "tradeType": "Long",
      "volumeLeverage": 11.9,
      "outcome": "consolidation",
      "converted": false,
      "watchlistTime": "2025-08-01T10:37:53.657Z",
      "lifetimeMinutes": 0,
      "createdAt": "2025-08-01T10:38:16.676Z"
    },
    {
      "symbol": "VVV/USDT",
      "anomalyId": "VVV_1754044976826",
      "tradeType": "Long",
      "volumeLeverage": 11.9,
      "outcome": "consolidation",
      "converted": false,
      "watchlistTime": "2025-08-01T10:42:56.826Z",
      "lifetimeMinutes": 0,
      "createdAt": "2025-08-01T10:43:17.542Z"
    },
    {
      "symbol": "AMP/USDT",
      "anomalyId": "AMP_1754045245062",
      "tradeType": "Short",
      "volumeLeverage": 11.1,
      "outcome": "consolidation",
      "converted": false,
      "watchlistTime": "2025-08-01T10:47:25.062Z",
      "lifetimeMinutes": 0,
      "createdAt": "2025-08-01T10:47:46.687Z"
    },
    {
      "symbol": "AMP/USDT",
      "anomalyId": "AMP_1754045501536",
      "tradeType": "Short",
      "volumeLeverage": 11.1,
      "outcome": "consolidation",
      "converted": false,
      "watchlistTime": "2025-08-01T10:51:41.536Z",
      "lifetimeMinutes": 0,
      "createdAt": "2025-08-01T10:51:46.646Z"
    },
    {
      "symbol": "AMP/USDT",
      "anomalyId": "AMP_1754045802036",
      "tradeType": "Short",
      "volumeLeverage": 11.1,
      "outcome": "consolidation",
      "converted": false,
      "watchlistTime": "2025-08-01T10:56:42.036Z",
      "lifetimeMinutes": 0,
      "createdAt": "2025-08-01T10:56:46.972Z"
    },
    {
      "symbol": "IOTX/USDT",
      "anomalyId": "IOTX_1754046107637",
      "tradeType": "Long",
      "volumeLeverage": 16.1,
      "outcome": "consolidation",
      "converted": false,
      "watchlistTime": "2025-08-01T11:01:47.637Z",
      "lifetimeMinutes": 0,
      "createdAt": "2025-08-01T11:02:16.909Z"
    },
    {
      "symbol": "IOTX/USDT",
      "anomalyId": "IOTX_1754046411653",
      "tradeType": "Long",
      "volumeLeverage": 16.1,
      "outcome": "consolidation",
      "converted": false,
      "watchlistTime": "2025-08-01T11:06:51.653Z",
      "lifetimeMinutes": 0,
      "createdAt": "2025-08-01T11:07:17.007Z"
    },
    {
      "symbol": "IOTX/USDT",
      "anomalyId": "IOTX_1754046712107",
      "tradeType": "Long",
      "volumeLeverage": 16.1,
      "outcome": "consolidation",
      "converted": false,
      "watchlistTime": "2025-08-01T11:11:52.107Z",
      "lifetimeMinutes": 0,
      "createdAt": "2025-08-01T11:12:16.919Z"
    },
    {
      "symbol": "SUN/USDT",
      "anomalyId": "SUN_1754047908314",
      "tradeType": "Short",
      "volumeLeverage": 8.3,
      "outcome": "cancel",
      "converted": false,
      "watchlistTime": "2025-08-01T11:31:48.314Z",
      "lifetimeMinutes": 37,
      "createdAt": "2025-08-01T12:08:49.717Z"
    }
  ],
  "totalLeads": 238,
  "convertedToTrade": 6,
  "averageLeadLifetimeMinutes": 2.5,
  "lastUpdated": "2025-08-01T12:08:49.720Z"
}